pmbec/__init__.py
pmbec/pmbec_generator.py
pmbec/reduced_cysteine_raw_data/Cysteine_surrogate_raw_data.csv
pmbec/reduced_cysteine_raw_data/__init__.py
pmbec/tests/__init__.py
pmbec/tests/pmbec_generator_tests.py
pmbec/true_matrix/__init__.py
pmbec/true_matrix/covariance_matrix.mat
pmbec/true_matrix/__pycache__/__init__.cpython-38.pyc
pmbec-0.0.2.dist-info/LICENSE
pmbec-0.0.2.dist-info/METADATA
pmbec-0.0.2.dist-info/WHEEL
pmbec-0.0.2.dist-info/top_level.txt
pmbec-0.0.2.dist-info/RECORD
