Metadata-Version: 2.1
Name: pmbec
Version: 0.0.2
Summary: creates, visualizes, and exports peptide to MHC binding energy covariance (pmbec) matrices
Home-page: https://github.com/IEDB/PMBEC
Author: Jacob Doering-Powell
Author-email: jacobdoeringpowell@gmail.com
License: UNKNOWN
Platform: UNKNOWN
Classifier: Programming Language :: Python :: 3
Classifier: License :: OSI Approved
Classifier: Operating System :: Unix
Requires-Python: >=3.7
Requires-Dist: pandas
Requires-Dist: numpy
Requires-Dist: matplotlib
Requires-Dist: openpyxl
Requires-Dist: Jinja2
Requires-Dist: seaborn
Requires-Dist: scipy
